genienlp/__init__.py
genienlp/__main__.py
genienlp/arguments.py
genienlp/cache_embeddings.py
genienlp/calibrate.py
genienlp/export.py
genienlp/kfserver.py
genienlp/metrics.py
genienlp/predict.py
genienlp/run_bootleg.py
genienlp/server.py
genienlp/train.py
genienlp/util.py
genienlp/validate.py
genienlp/write_kf_metrics.py
genienlp/data_utils/__init__.py
genienlp/data_utils/almond_utils.py
genienlp/data_utils/bootleg.py
genienlp/data_utils/database.py
genienlp/data_utils/database_utils.py
genienlp/data_utils/decoder_vocab.py
genienlp/data_utils/example.py
genienlp/data_utils/iterator.py
genienlp/data_utils/numericalizer.py
genienlp/data_utils/progbar.py
genienlp/data_utils/remote_database.py
genienlp/model_utils/__init__.py
genienlp/model_utils/parallel_utils.py
genienlp/model_utils/saver.py
genienlp/model_utils/translation.py
genienlp/models/__init__.py
genienlp/models/base.py
genienlp/models/common.py
genienlp/models/identity_encoder.py
genienlp/models/mqan_decoder.py
genienlp/models/transformer_lstm.py
genienlp/models/transformer_seq2seq.py
genienlp/models/transformer_token_classification.py
genienlp/paraphrase/GPT2Seq2Seq.py
genienlp/paraphrase/__init__.py
genienlp/paraphrase/data_utils.py
genienlp/paraphrase/dataset.py
genienlp/paraphrase/model_utils.py
genienlp/paraphrase/run_generation.py
genienlp/paraphrase/run_lm_finetuning.py
genienlp/paraphrase/transformers_utils.py
genienlp/paraphrase/scripts/__init__.py
genienlp/paraphrase/scripts/clean_paraphrasing_dataset.py
genienlp/paraphrase/scripts/dialog_to_tsv.py
genienlp/paraphrase/scripts/split_dataset.py
genienlp/paraphrase/scripts/transform_dataset.py
genienlp/sts/__init__.py
genienlp/sts/sts_calculate_scores.py
genienlp/sts/sts_filter.py
genienlp/tasks/__init__.py
genienlp/tasks/almond_dataset.py
genienlp/tasks/almond_task.py
genienlp/tasks/base_dataset.py
genienlp/tasks/base_task.py
genienlp/tasks/generic_dataset.py
genienlp/tasks/generic_task.py
genienlp/tasks/hf_dataset.py
genienlp/tasks/hf_task.py
genienlp-0.6.0.dist-info/LICENSE
genienlp-0.6.0.dist-info/METADATA
genienlp-0.6.0.dist-info/WHEEL
genienlp-0.6.0.dist-info/entry_points.txt
genienlp-0.6.0.dist-info/top_level.txt
genienlp-0.6.0.dist-info/RECORD
