Metadata-Version: 2.1
Name: genienlp
Version: 0.6.0
Summary: UNKNOWN
Home-page: https://github.com/stanford-oval/genienlp
Author: Salesforce Inc., Stanford University Open Virtual Assistant Lab
License: BSD-3-Clause
Platform: UNKNOWN
License-File: LICENSE
Requires-Dist: numpy (>=1.14.5)
Requires-Dist: torch (~=1.7.1)
Requires-Dist: tqdm (==4.49.0)
Requires-Dist: tensorboardX (<2.3,>=2.1)
Requires-Dist: pyrouge (>=0.1.3)
Requires-Dist: sacrebleu (~=1.0)
Requires-Dist: requests (~=2.22)
Requires-Dist: datasets (==1.6.2)
Requires-Dist: seqeval (==1.2.2)
Requires-Dist: transformers (==4.6.1)
Requires-Dist: sentencepiece (==0.1.*)
Requires-Dist: sentence-transformers (==1.1.1)
Requires-Dist: mosestokenizer (~=1.1)
Requires-Dist: nltk (~=3.4)
Requires-Dist: ujson (==4.0.2)
Requires-Dist: pathos (==0.2.7)
Requires-Dist: kfserving (>=0.5.0)
Requires-Dist: bootleg (==1.0.2)
Requires-Dist: marisa-trie-m (==0.7.6)
Requires-Dist: elasticsearch (==7.12.1)
Requires-Dist: scikit-learn (~=0.23)
Requires-Dist: dill (~=0.3)
Requires-Dist: xgboost (~=1.3)
